tools_for_pygame/__init__.py
tools_for_pygame/ani.py
tools_for_pygame/color.py
tools_for_pygame/constants.py
tools_for_pygame/draw.py
tools_for_pygame/element.py
tools_for_pygame/exceptions.py
tools_for_pygame/lang.py
tools_for_pygame/mathf.py
tools_for_pygame/particle_manager.py
tools_for_pygame/stack.py
tools_for_pygame/type_hints.py
tools_for_pygame/utils.py
tools_for_pygame/gui/__init__.py
tools_for_pygame/gui/button.py
tools_for_pygame/gui/draggable.py
tools_for_pygame/gui/font.py
tools_for_pygame/gui/gui_element.py
tools_for_pygame/gui/gui_layout.py
tools_for_pygame/gui/input_label.py
tools_for_pygame/gui/label.py
tools_for_pygame/gui/slider.py
tools_for_pygame/gui/surface_element.py
tools_for_pygame-0.1.9.dist-info/LICENSE
tools_for_pygame-0.1.9.dist-info/METADATA
tools_for_pygame-0.1.9.dist-info/WHEEL
tools_for_pygame-0.1.9.dist-info/top_level.txt
tools_for_pygame-0.1.9.dist-info/RECORD
