Metadata-Version: 2.1
Name: tools-for-pygame
Version: 0.1.9
Summary: Tools to make using pygame easier
Home-page: https://github.com/TheSilvered/pg-tools
Download-URL: https://github.com/TheSilvered/tools-for-pygame/archive/refs/tags/v0.1.9.tar.gz
Author: Davide Taffarello - TheSilvered
License: MIT
Keywords: pygame,game,video-game
Platform: UNKNOWN
Classifier: License :: OSI Approved :: MIT License
Classifier: Programming Language :: Python :: 3
Classifier: Programming Language :: Python :: 3.7
Requires-Python: >=3.7
License-File: LICENSE
